aamraz/__init__.py
aamraz/embedding.py
aamraz/normalizer.py
aamraz/stemmer.py
aamraz/util.py
aamraz/word_tokenizer.py
aamraz/test/__init__.py
aamraz/test/embedding_test.py
aamraz/test/ngram_test.py
aamraz/test/sample.py
aamraz/test/stemmer_test.py
aamraz/test/stop_words_test.py
aamraz-0.1.0.dist-info/METADATA
aamraz-0.1.0.dist-info/WHEEL
aamraz-0.1.0.dist-info/top_level.txt
aamraz-0.1.0.dist-info/RECORD
