Metadata-Version: 2.1
Name: aamraz
Version: 0.1.0
Summary: This project is a collection of Natural Language Processing tools for Kurdish Language.
Home-page: https://github.com/MohammadDevelop/Aamraz
Author: Mohammad Mahmoodi Varnamkhasti
Author-email: research@amzmohammad.com
Classifier: Programming Language :: Python :: 3
Classifier: License :: OSI Approved :: MIT License
Classifier: Operating System :: OS Independent
Requires-Python: >=3.6
Requires-Dist: numpy >=1.24.0
Requires-Dist: fasttext >=0.9.3
Requires-Dist: gensim >=4.3.3
